Classfile /Users/xcoulon/code/lambdamatic/lambdamatic-analyzer/target/test-classes/org/lambdamatic/analyzer/IsolatedLambdaBytecodeAnalyzerTest.class
  Last modified Oct 26, 2016; size 3316 bytes
  MD5 checksum 2b1e9711fc8b784e78992d3e1b9cf412
  Compiled from "IsolatedLambdaBytecodeAnalyzerTest.java"
public class org.lambdamatic.analyzer.IsolatedLambdaBytecodeAnalyzerTest
  minor version: 0
  major version: 52
  flags: ACC_PUBLIC, ACC_SUPER
Constant pool:
    #1 = Class              #2            // org/lambdamatic/analyzer/IsolatedLambdaBytecodeAnalyzerTest
    #2 = Utf8               org/lambdamatic/analyzer/IsolatedLambdaBytecodeAnalyzerTest
    #3 = Class              #4            // java/lang/Object
    #4 = Utf8               java/lang/Object
    #5 = Utf8               LOGGER
    #6 = Utf8               Lorg/slf4j/Logger;
    #7 = Utf8               analyzer
    #8 = Utf8               Lorg/lambdamatic/analyzer/LambdaExpressionAnalyzer;
    #9 = Utf8               <clinit>
   #10 = Utf8               ()V
   #11 = Utf8               Code
   #12 = Methodref          #13.#15       // org/slf4j/LoggerFactory.getLogger:(Ljava/lang/Class;)Lorg/slf4j/Logger;
   #13 = Class              #14           // org/slf4j/LoggerFactory
   #14 = Utf8               org/slf4j/LoggerFactory
   #15 = NameAndType        #16:#17       // getLogger:(Ljava/lang/Class;)Lorg/slf4j/Logger;
   #16 = Utf8               getLogger
   #17 = Utf8               (Ljava/lang/Class;)Lorg/slf4j/Logger;
   #18 = Fieldref           #1.#19        // org/lambdamatic/analyzer/IsolatedLambdaBytecodeAnalyzerTest.LOGGER:Lorg/slf4j/Logger;
   #19 = NameAndType        #5:#6         // LOGGER:Lorg/slf4j/Logger;
   #20 = Utf8               LineNumberTable
   #21 = Utf8               LocalVariableTable
   #22 = Utf8               <init>
   #23 = Methodref          #3.#24        // java/lang/Object."<init>":()V
   #24 = NameAndType        #22:#10       // "<init>":()V
   #25 = Methodref          #26.#28       // org/lambdamatic/analyzer/LambdaExpressionAnalyzer.getInstance:()Lorg/lambdamatic/analyzer/LambdaExpressionAnalyzer;
   #26 = Class              #27           // org/lambdamatic/analyzer/LambdaExpressionAnalyzer
   #27 = Utf8               org/lambdamatic/analyzer/LambdaExpressionAnalyzer
   #28 = NameAndType        #29:#30       // getInstance:()Lorg/lambdamatic/analyzer/LambdaExpressionAnalyzer;
   #29 = Utf8               getInstance
   #30 = Utf8               ()Lorg/lambdamatic/analyzer/LambdaExpressionAnalyzer;
   #31 = Fieldref           #1.#32        // org/lambdamatic/analyzer/IsolatedLambdaBytecodeAnalyzerTest.analyzer:Lorg/lambdamatic/analyzer/LambdaExpressionAnalyzer;
   #32 = NameAndType        #7:#8         // analyzer:Lorg/lambdamatic/analyzer/LambdaExpressionAnalyzer;
   #33 = Utf8               this
   #34 = Utf8               Lorg/lambdamatic/analyzer/IsolatedLambdaBytecodeAnalyzerTest;
   #35 = Utf8               shouldParseExpression
   #36 = Utf8               Exceptions
   #37 = Class              #38           // java/io/IOException
   #38 = Utf8               java/io/IOException
   #39 = Class              #40           // java/lang/NoSuchMethodException
   #40 = Utf8               java/lang/NoSuchMethodException
   #41 = Class              #42           // java/lang/SecurityException
   #42 = Utf8               java/lang/SecurityException
   #43 = Utf8               RuntimeVisibleAnnotations
   #44 = Utf8               Lorg/junit/Test;
   #45 = NameAndType        #46:#47       // accept:()Lorg/lambdamatic/SerializableConsumer;
   #46 = Utf8               accept
   #47 = Utf8               ()Lorg/lambdamatic/SerializableConsumer;
   #48 = InvokeDynamic      #0:#45        // #0:accept:()Lorg/lambdamatic/SerializableConsumer;
   #49 = Methodref          #26.#50       // org/lambdamatic/analyzer/LambdaExpressionAnalyzer.analyzeExpression:(Ljava/lang/Object;)Lorg/lambdamatic/analyzer/ast/node/LambdaExpression;
   #50 = NameAndType        #51:#52       // analyzeExpression:(Ljava/lang/Object;)Lorg/lambdamatic/analyzer/ast/node/LambdaExpression;
   #51 = Utf8               analyzeExpression
   #52 = Utf8               (Ljava/lang/Object;)Lorg/lambdamatic/analyzer/ast/node/LambdaExpression;
   #53 = Utf8               expression
   #54 = Utf8               Lorg/lambdamatic/SerializableConsumer;
   #55 = Utf8               resultExpression
   #56 = Utf8               Lorg/lambdamatic/analyzer/ast/node/LambdaExpression;
   #57 = Utf8               LocalVariableTypeTable
   #58 = Utf8               Lorg/lambdamatic/SerializableConsumer<Ljava/lang/String;>;
   #59 = Utf8               factory
   #60 = Utf8               (Ljava/util/function/Supplier;)Lcom/sample/model/TestPojo;
   #61 = Utf8               Signature
   #62 = Utf8               (Ljava/util/function/Supplier<Lcom/sample/model/TestPojo;>;)Lcom/sample/model/TestPojo;
   #63 = InterfaceMethodref #64.#66       // java/util/function/Supplier.get:()Ljava/lang/Object;
   #64 = Class              #65           // java/util/function/Supplier
   #65 = Utf8               java/util/function/Supplier
   #66 = NameAndType        #67:#68       // get:()Ljava/lang/Object;
   #67 = Utf8               get
   #68 = Utf8               ()Ljava/lang/Object;
   #69 = Class              #70           // com/sample/model/TestPojo
   #70 = Utf8               com/sample/model/TestPojo
   #71 = Utf8               supplier
   #72 = Utf8               Ljava/util/function/Supplier;
   #73 = Utf8               Ljava/util/function/Supplier<Lcom/sample/model/TestPojo;>;
   #74 = Utf8               $deserializeLambda$
   #75 = Utf8               (Ljava/lang/invoke/SerializedLambda;)Ljava/lang/Object;
   #76 = Methodref          #77.#79       // java/lang/invoke/SerializedLambda.getImplMethodName:()Ljava/lang/String;
   #77 = Class              #78           // java/lang/invoke/SerializedLambda
   #78 = Utf8               java/lang/invoke/SerializedLambda
   #79 = NameAndType        #80:#81       // getImplMethodName:()Ljava/lang/String;
   #80 = Utf8               getImplMethodName
   #81 = Utf8               ()Ljava/lang/String;
   #82 = Methodref          #83.#85       // java/lang/String.hashCode:()I
   #83 = Class              #84           // java/lang/String
   #84 = Utf8               java/lang/String
   #85 = NameAndType        #86:#87       // hashCode:()I
   #86 = Utf8               hashCode
   #87 = Utf8               ()I
   #88 = String             #22           // <init>
   #89 = Methodref          #83.#90       // java/lang/String.equals:(Ljava/lang/Object;)Z
   #90 = NameAndType        #91:#92       // equals:(Ljava/lang/Object;)Z
   #91 = Utf8               equals
   #92 = Utf8               (Ljava/lang/Object;)Z
   #93 = Methodref          #77.#94       // java/lang/invoke/SerializedLambda.getImplMethodKind:()I
   #94 = NameAndType        #95:#87       // getImplMethodKind:()I
   #95 = Utf8               getImplMethodKind
   #96 = Methodref          #77.#97       // java/lang/invoke/SerializedLambda.getFunctionalInterfaceClass:()Ljava/lang/String;
   #97 = NameAndType        #98:#81       // getFunctionalInterfaceClass:()Ljava/lang/String;
   #98 = Utf8               getFunctionalInterfaceClass
   #99 = String             #100          // org/lambdamatic/SerializableConsumer
  #100 = Utf8               org/lambdamatic/SerializableConsumer
  #101 = Methodref          #3.#90        // java/lang/Object.equals:(Ljava/lang/Object;)Z
  #102 = Methodref          #77.#103      // java/lang/invoke/SerializedLambda.getFunctionalInterfaceMethodName:()Ljava/lang/String;
  #103 = NameAndType        #104:#81      // getFunctionalInterfaceMethodName:()Ljava/lang/String;
  #104 = Utf8               getFunctionalInterfaceMethodName
  #105 = String             #46           // accept
  #106 = Methodref          #77.#107      // java/lang/invoke/SerializedLambda.getFunctionalInterfaceMethodSignature:()Ljava/lang/String;
  #107 = NameAndType        #108:#81      // getFunctionalInterfaceMethodSignature:()Ljava/lang/String;
  #108 = Utf8               getFunctionalInterfaceMethodSignature
  #109 = String             #110          // (Ljava/lang/Object;)V
  #110 = Utf8               (Ljava/lang/Object;)V
  #111 = Methodref          #77.#112      // java/lang/invoke/SerializedLambda.getImplClass:()Ljava/lang/String;
  #112 = NameAndType        #113:#81      // getImplClass:()Ljava/lang/String;
  #113 = Utf8               getImplClass
  #114 = String             #70           // com/sample/model/TestPojo
  #115 = Methodref          #77.#116      // java/lang/invoke/SerializedLambda.getImplMethodSignature:()Ljava/lang/String;
  #116 = NameAndType        #117:#81      // getImplMethodSignature:()Ljava/lang/String;
  #117 = Utf8               getImplMethodSignature
  #118 = String             #119          // (Ljava/lang/String;)V
  #119 = Utf8               (Ljava/lang/String;)V
  #120 = InvokeDynamic      #0:#45        // #0:accept:()Lorg/lambdamatic/SerializableConsumer;
  #121 = Class              #122          // java/lang/IllegalArgumentException
  #122 = Utf8               java/lang/IllegalArgumentException
  #123 = String             #124          // Invalid lambda deserialization
  #124 = Utf8               Invalid lambda deserialization
  #125 = Methodref          #121.#126     // java/lang/IllegalArgumentException."<init>":(Ljava/lang/String;)V
  #126 = NameAndType        #22:#119      // "<init>":(Ljava/lang/String;)V
  #127 = Utf8               StackMapTable
  #128 = Utf8               SourceFile
  #129 = Utf8               IsolatedLambdaBytecodeAnalyzerTest.java
  #130 = Utf8               BootstrapMethods
  #131 = Methodref          #132.#134     // java/lang/invoke/LambdaMetafactory.altMetafactory:(Ljava/lang/invoke/MethodHandles$Lookup;Ljava/lang/String;Ljava/lang/invoke/MethodType;[Ljava/lang/Object;)Ljava/lang/invoke/CallSite;
  #132 = Class              #133          // java/lang/invoke/LambdaMetafactory
  #133 = Utf8               java/lang/invoke/LambdaMetafactory
  #134 = NameAndType        #135:#136     // altMetafactory:(Ljava/lang/invoke/MethodHandles$Lookup;Ljava/lang/String;Ljava/lang/invoke/MethodType;[Ljava/lang/Object;)Ljava/lang/invoke/CallSite;
  #135 = Utf8               altMetafactory
  #136 = Utf8               (Ljava/lang/invoke/MethodHandles$Lookup;Ljava/lang/String;Ljava/lang/invoke/MethodType;[Ljava/lang/Object;)Ljava/lang/invoke/CallSite;
  #137 = MethodHandle       #6:#131       // invokestatic java/lang/invoke/LambdaMetafactory.altMetafactory:(Ljava/lang/invoke/MethodHandles$Lookup;Ljava/lang/String;Ljava/lang/invoke/MethodType;[Ljava/lang/Object;)Ljava/lang/invoke/CallSite;
  #138 = MethodType         #110          //  (Ljava/lang/Object;)V
  #139 = Methodref          #69.#126      // com/sample/model/TestPojo."<init>":(Ljava/lang/String;)V
  #140 = MethodHandle       #8:#139       // newinvokespecial com/sample/model/TestPojo."<init>":(Ljava/lang/String;)V
  #141 = MethodType         #119          //  (Ljava/lang/String;)V
  #142 = Integer            1
  #143 = Utf8               InnerClasses
  #144 = Class              #145          // java/lang/invoke/MethodHandles$Lookup
  #145 = Utf8               java/lang/invoke/MethodHandles$Lookup
  #146 = Class              #147          // java/lang/invoke/MethodHandles
  #147 = Utf8               java/lang/invoke/MethodHandles
  #148 = Utf8               Lookup
{
  private static final org.slf4j.Logger LOGGER;
    descriptor: Lorg/slf4j/Logger;
    flags: ACC_PRIVATE, ACC_STATIC, ACC_FINAL

  private final org.lambdamatic.analyzer.LambdaExpressionAnalyzer analyzer;
    descriptor: Lorg/lambdamatic/analyzer/LambdaExpressionAnalyzer;
    flags: ACC_PRIVATE, ACC_FINAL

  static {};
    descriptor: ()V
    flags: ACC_STATIC
    Code:
      stack=1, locals=0, args_size=0
         0: ldc           #1                  // class org/lambdamatic/analyzer/IsolatedLambdaBytecodeAnalyzerTest
         2: invokestatic  #12                 // Method org/slf4j/LoggerFactory.getLogger:(Ljava/lang/Class;)Lorg/slf4j/Logger;
         5: putstatic     #18                 // Field LOGGER:Lorg/slf4j/Logger;
         8: return
      LineNumberTable:
        line 30: 0
        line 29: 5
        line 30: 8
      LocalVariableTable:
        Start  Length  Slot  Name   Signature

  public org.lambdamatic.analyzer.IsolatedLambdaBytecodeAnalyzerTest();
    descriptor: ()V
    flags: ACC_PUBLIC
    Code:
      stack=2, locals=1, args_size=1
         0: aload_0
         1: invokespecial #23                 // Method java/lang/Object."<init>":()V
         4: aload_0
         5: invokestatic  #25                 // Method org/lambdamatic/analyzer/LambdaExpressionAnalyzer.getInstance:()Lorg/lambdamatic/analyzer/LambdaExpressionAnalyzer;
         8: putfield      #31                 // Field analyzer:Lorg/lambdamatic/analyzer/LambdaExpressionAnalyzer;
        11: return
      LineNumberTable:
        line 27: 0
        line 32: 4
        line 27: 11
      LocalVariableTable:
        Start  Length  Slot  Name   Signature
            0      12     0  this   Lorg/lambdamatic/analyzer/IsolatedLambdaBytecodeAnalyzerTest;

  public void shouldParseExpression() throws java.io.IOException, java.lang.NoSuchMethodException, java.lang.SecurityException;
    descriptor: ()V
    flags: ACC_PUBLIC
    Exceptions:
      throws java.io.IOException, java.lang.NoSuchMethodException, java.lang.SecurityException
    RuntimeVisibleAnnotations:
      0: #44()
    Code:
      stack=2, locals=3, args_size=1
         0: invokedynamic #48,  0             // InvokeDynamic #0:accept:()Lorg/lambdamatic/SerializableConsumer;
         5: astore_1
         6: aload_0
         7: getfield      #31                 // Field analyzer:Lorg/lambdamatic/analyzer/LambdaExpressionAnalyzer;
        10: aload_1
        11: invokevirtual #49                 // Method org/lambdamatic/analyzer/LambdaExpressionAnalyzer.analyzeExpression:(Ljava/lang/Object;)Lorg/lambdamatic/analyzer/ast/node/LambdaExpression;
        14: astore_2
        15: return
      LineNumberTable:
        line 38: 0
        line 37: 5
        line 43: 6
        line 48: 15
      LocalVariableTable:
        Start  Length  Slot  Name   Signature
            0      16     0  this   Lorg/lambdamatic/analyzer/IsolatedLambdaBytecodeAnalyzerTest;
            6      10     1 expression   Lorg/lambdamatic/SerializableConsumer;
           15       1     2 resultExpression   Lorg/lambdamatic/analyzer/ast/node/LambdaExpression;
      LocalVariableTypeTable:
        Start  Length  Slot  Name   Signature
            6      10     1 expression   Lorg/lambdamatic/SerializableConsumer<Ljava/lang/String;>;

  private com.sample.model.TestPojo factory(java.util.function.Supplier<com.sample.model.TestPojo>);
    descriptor: (Ljava/util/function/Supplier;)Lcom/sample/model/TestPojo;
    flags: ACC_PRIVATE
    Signature: #62                          // (Ljava/util/function/Supplier<Lcom/sample/model/TestPojo;>;)Lcom/sample/model/TestPojo;
    Code:
      stack=1, locals=2, args_size=2
         0: aload_1
         1: invokeinterface #63,  1           // InterfaceMethod java/util/function/Supplier.get:()Ljava/lang/Object;
         6: checkcast     #69                 // class com/sample/model/TestPojo
         9: areturn
      LineNumberTable:
        line 51: 0
      LocalVariableTable:
        Start  Length  Slot  Name   Signature
            0      10     0  this   Lorg/lambdamatic/analyzer/IsolatedLambdaBytecodeAnalyzerTest;
            0      10     1 supplier   Ljava/util/function/Supplier;
      LocalVariableTypeTable:
        Start  Length  Slot  Name   Signature
            0      10     1 supplier   Ljava/util/function/Supplier<Lcom/sample/model/TestPojo;>;

  private static java.lang.Object $deserializeLambda$(java.lang.invoke.SerializedLambda);
    descriptor: (Ljava/lang/invoke/SerializedLambda;)Ljava/lang/Object;
    flags: ACC_PRIVATE, ACC_STATIC, ACC_SYNTHETIC
    Code:
      stack=3, locals=3, args_size=1
         0: aload_0
         1: invokevirtual #76                 // Method java/lang/invoke/SerializedLambda.getImplMethodName:()Ljava/lang/String;
         4: astore_1
         5: iconst_m1
         6: istore_2
         7: aload_1
         8: invokevirtual #82                 // Method java/lang/String.hashCode:()I
        11: lookupswitch  { // 1
              1818100338: 28
                 default: 39
            }
        28: aload_1
        29: ldc           #88                 // String <init>
        31: invokevirtual #89                 // Method java/lang/String.equals:(Ljava/lang/Object;)Z
        34: ifeq          39
        37: iconst_0
        38: istore_2
        39: iload_2
        40: lookupswitch  { // 1
                       0: 60
                 default: 135
            }
        60: aload_0
        61: invokevirtual #93                 // Method java/lang/invoke/SerializedLambda.getImplMethodKind:()I
        64: bipush        8
        66: if_icmpne     135
        69: aload_0
        70: invokevirtual #96                 // Method java/lang/invoke/SerializedLambda.getFunctionalInterfaceClass:()Ljava/lang/String;
        73: ldc           #99                 // String org/lambdamatic/SerializableConsumer
        75: invokevirtual #101                // Method java/lang/Object.equals:(Ljava/lang/Object;)Z
        78: ifeq          135
        81: aload_0
        82: invokevirtual #102                // Method java/lang/invoke/SerializedLambda.getFunctionalInterfaceMethodName:()Ljava/lang/String;
        85: ldc           #105                // String accept
        87: invokevirtual #101                // Method java/lang/Object.equals:(Ljava/lang/Object;)Z
        90: ifeq          135
        93: aload_0
        94: invokevirtual #106                // Method java/lang/invoke/SerializedLambda.getFunctionalInterfaceMethodSignature:()Ljava/lang/String;
        97: ldc           #109                // String (Ljava/lang/Object;)V
        99: invokevirtual #101                // Method java/lang/Object.equals:(Ljava/lang/Object;)Z
       102: ifeq          135
       105: aload_0
       106: invokevirtual #111                // Method java/lang/invoke/SerializedLambda.getImplClass:()Ljava/lang/String;
       109: ldc           #114                // String com/sample/model/TestPojo
       111: invokevirtual #101                // Method java/lang/Object.equals:(Ljava/lang/Object;)Z
       114: ifeq          135
       117: aload_0
       118: invokevirtual #115                // Method java/lang/invoke/SerializedLambda.getImplMethodSignature:()Ljava/lang/String;
       121: ldc           #118                // String (Ljava/lang/String;)V
       123: invokevirtual #101                // Method java/lang/Object.equals:(Ljava/lang/Object;)Z
       126: ifeq          135
       129: invokedynamic #120,  0            // InvokeDynamic #0:accept:()Lorg/lambdamatic/SerializableConsumer;
       134: areturn
       135: new           #121                // class java/lang/IllegalArgumentException
       138: dup
       139: ldc           #123                // String Invalid lambda deserialization
       141: invokespecial #125                // Method java/lang/IllegalArgumentException."<init>":(Ljava/lang/String;)V
       144: athrow
      LineNumberTable:
        line 1: 0
      LocalVariableTable:
        Start  Length  Slot  Name   Signature
      StackMapTable: number_of_entries = 4
        frame_type = 253 /* append */
          offset_delta = 28
          locals = [ class java/lang/String, int ]
        frame_type = 10 /* same */
        frame_type = 20 /* same */
        frame_type = 249 /* chop */
          offset_delta = 74
}
SourceFile: "IsolatedLambdaBytecodeAnalyzerTest.java"
BootstrapMethods:
  0: #137 invokestatic java/lang/invoke/LambdaMetafactory.altMetafactory:(Ljava/lang/invoke/MethodHandles$Lookup;Ljava/lang/String;Ljava/lang/invoke/MethodType;[Ljava/lang/Object;)Ljava/lang/invoke/CallSite;
    Method arguments:
      #138 (Ljava/lang/Object;)V
      #140 newinvokespecial com/sample/model/TestPojo."<init>":(Ljava/lang/String;)V
      #141 (Ljava/lang/String;)V
      #142 1
InnerClasses:
     public static final #148= #144 of #146; //Lookup=class java/lang/invoke/MethodHandles$Lookup of class java/lang/invoke/MethodHandles
